[
    {
        "cinemaId": null,
        "cinemaName": "asdas",
        "cinemaTotalCapacity": "21",
        "cinemaTicketPrice": "19",
        "cinemaAddress": "holiwi",
        "cinemaAvailability": "true"
    },
    {
        "cinemaId": null,
        "cinemaName": "cinecito",
        "cinemaTotalCapacity": null,
        "cinemaTicketPrice": null,
        "cinemaAddress": null,
        "cinemaAvailability": "true"
    },
    {
        "cinemaId": null,
        "cinemaName": "cinecito",
        "cinemaTotalCapacity": null,
        "cinemaTicketPrice": null,
        "cinemaAddress": null,
        "cinemaAvailability": "true"
    },
    {
        "cinemaId": null,
        "cinemaName": "Cine 1",
        "cinemaTotalCapacity": "21",
        "cinemaTicketPrice": "19",
        "cinemaAddress": "holiwi",
        "cinemaAvailability": "true"
    },
    {
        "cinemaId": "4",
        "cinemaName": "nuevo",
        "cinemaTotalCapacity": "878",
        "cinemaTicketPrice": "120",
        "cinemaAddress": "holi",
        "cinemaAvailability": "false"
    }
]